mypackage/__init__.py
mypackage/categorical.py
mypackage/data_description.py
mypackage/download.py
mypackage/feature_scaling.py
mypackage/imputation.py
CLI_processor-1.0.0.dist-info/METADATA
CLI_processor-1.0.0.dist-info/WHEEL
CLI_processor-1.0.0.dist-info/entry_points.txt
CLI_processor-1.0.0.dist-info/top_level.txt
CLI_processor-1.0.0.dist-info/RECORD
